{
  "protocol_version" : "0.0.6",
  "configuration" : {
    "version" : "(6.10.0.104) (2019-12/5d03a6fe116)",
    "tlc" : "normal",
    "sigsgev" : "altstack",
    "notifications" : "kqueue",
    "architecture" : "amd64",
    "disabled_features" : "none",
    "smallconfig" : "disabled",
    "bigarrays" : "disabled",
    "softdebug" : "enabled",
    "interpreter" : "enabled",
    "llvm_support" : "0",
    "suspend" : "hybrid"
  },
  "memory" : {
    "Resident Size" : "162930688",
    "Virtual Size" : "4590133248",
    "minor_gc_time" : "538089",
    "major_gc_time" : "0",
    "minor_gc_count" : "1",
    "major_gc_count" : "0",
    "major_gc_time_concurrent" : "0"
 },
  "threads" : [
 {
    "is_managed" : false,
    "offset_free_hash" : "0x0",
    "offset_rich_hash" : "0x0",
    "crashed" : false,
    "native_thread_id" : "0x11871f5c0",
    "thread_info_addr" : "0x7ffb31001000",
    "thread_name" : "tid_307",
    "ctx" : {
      "IP" : "0x7fff793ea1b2",
      "SP" : "0x7ffee6d08bc8",
      "BP" : "0x7ffee6d08c50"
  },
    "unmanaged_frames" : [
  {
      "is_managed" : "false",
      "native_address" : "0x108fa7346",
      "native_offset" : "0x00000"
   }
,
  {
      "is_managed" : "false",
      "native_address" : "0x109141aa5",
      "native_offset" : "0x00000"
   }
,
  {
      "is_managed" : "false",
      "native_address" : "0x1091417d7",
      "native_offset" : "0x00000"
   }
,
  {
      "is_managed" : "false",
      "native_address" : "0x109012ce0",
      "native_offset" : "0x00000"
   }
,
  {
      "is_managed" : "false",
      "native_address" : "0x7fff79497b3d",
      "native_offset" : "0x00000"
   }
,
  {
      "is_managed" : "false",
      "native_address" : "0x108fa997c",
      "native_offset" : "0x00000"
   }
,
  {
      "is_managed" : "false",
      "native_address" : "0x1091ee430",
      "native_offset" : "0x00000"
   }
,
  {
      "is_managed" : "false",
      "native_address" : "0x109206401",
      "native_offset" : "0x00000"
   }
,
  {
      "is_managed" : "false",
      "native_address" : "0x10913e9e4",
      "native_offset" : "0x00000"
   }
,
  {
      "is_managed" : "false",
      "native_address" : "0x10913e7ea",
      "native_offset" : "0x00000"
   }
,
  {
      "is_managed" : "false",
      "native_address" : "0x108f6d30a",
      "native_offset" : "0x00000"
   }
,
  {
      "is_managed" : "false",
      "native_address" : "0x108ef8e49",
      "native_offset" : "0x00000"
   }
,
  {
      "is_managed" : "false",
      "native_address" : "0x7fff792ae08d",
      "native_offset" : "0x00000"
   }

  ]
 },
 {
    "is_managed" : true,
    "offset_free_hash" : "0x1cfb5decbf",
    "offset_rich_hash" : "0x1cfb5df079",
    "crashed" : true,
    "native_thread_id" : "0x70000e018000",
    "thread_info_addr" : "0x7ffb31087800",
    "thread_name" : "Thread Pool Worker",
    "ctx" : {
      "IP" : "0x7fff793ecb86",
      "SP" : "0x70000e0165a8",
      "BP" : "0x70000e0165e0"
  },
    "managed_frames" : [
  {
      "is_managed" : "false",
      "native_address" : "unregistered"
   }
,
  {
      "is_managed" : "true",
      "guid" : "55ADAE45-46CD-485B-A70E-2948332EBE8C",
      "token" : "0x00000",
      "native_offset" : "0x0",
      "filename" : "mscorlib.dll",
      "sizeofimage" : "0x474000",
      "timestamp" : "0xcdf122ed",
      "il_offset" : "0x0000c"
   }
,
  {
      "is_managed" : "true",
      "guid" : "55ADAE45-46CD-485B-A70E-2948332EBE8C",
      "token" : "0x6001f8c",
      "native_offset" : "0x0",
      "filename" : "mscorlib.dll",
      "sizeofimage" : "0x474000",
      "timestamp" : "0xcdf122ed",
      "il_offset" : "0x0001a"
   }
,
  {
      "is_managed" : "true",
      "guid" : "55ADAE45-46CD-485B-A70E-2948332EBE8C",
      "token" : "0x6001f32",
      "native_offset" : "0x0",
      "filename" : "mscorlib.dll",
      "sizeofimage" : "0x474000",
      "timestamp" : "0xcdf122ed",
      "il_offset" : "0x00028"
   }
,
  {
      "is_managed" : "true",
      "guid" : "55ADAE45-46CD-485B-A70E-2948332EBE8C",
      "token" : "0x6001f30",
      "native_offset" : "0x0",
      "filename" : "mscorlib.dll",
      "sizeofimage" : "0x474000",
      "timestamp" : "0xcdf122ed",
      "il_offset" : "0x00002"
   }
,
  {
      "is_managed" : "true",
      "guid" : "E5BBCD86-B476-47FC-970E-F00D99CDBAB3",
      "token" : "0x6000084",
      "native_offset" : "0x0",
      "filename" : "MonoDevelop.MSBuildBuilder.exe",
      "sizeofimage" : "0x18000",
      "timestamp" : "0xc077b0d4",
      "il_offset" : "0x000ae"
   }
,
  {
      "is_managed" : "true",
      "guid" : "E5BBCD86-B476-47FC-970E-F00D99CDBAB3",
      "token" : "0x6000083",
      "native_offset" : "0x0",
      "filename" : "MonoDevelop.MSBuildBuilder.exe",
      "sizeofimage" : "0x18000",
      "timestamp" : "0xc077b0d4",
      "il_offset" : "0x00001"
   }
,
  {
      "is_managed" : "true",
      "guid" : "E5BBCD86-B476-47FC-970E-F00D99CDBAB3",
      "token" : "0x600006a",
      "native_offset" : "0x0",
      "filename" : "MonoDevelop.MSBuildBuilder.exe",
      "sizeofimage" : "0x18000",
      "timestamp" : "0xc077b0d4",
      "il_offset" : "0x00048"
   }
,
  {
      "is_managed" : "true",
      "guid" : "E5BBCD86-B476-47FC-970E-F00D99CDBAB3",
      "token" : "0x60000a1",
      "native_offset" : "0x0",
      "filename" : "MonoDevelop.MSBuildBuilder.exe",
      "sizeofimage" : "0x18000",
      "timestamp" : "0xc077b0d4",
      "il_offset" : "0x00001"
   }
,
  {
      "is_managed" : "true",
      "guid" : "E5BBCD86-B476-47FC-970E-F00D99CDBAB3",
      "token" : "0x6000067",
      "native_offset" : "0x0",
      "filename" : "MonoDevelop.MSBuildBuilder.exe",
      "sizeofimage" : "0x18000",
      "timestamp" : "0xc077b0d4",
      "il_offset" : "0x00001"
   }
,
  {
      "is_managed" : "true",
      "guid" : "E5BBCD86-B476-47FC-970E-F00D99CDBAB3",
      "token" : "0x6000075",
      "native_offset" : "0x0",
      "filename" : "MonoDevelop.MSBuildBuilder.exe",
      "sizeofimage" : "0x18000",
      "timestamp" : "0xc077b0d4",
      "il_offset" : "0x00057"
   }
,
  {
      "is_managed" : "true",
      "guid" : "E5BBCD86-B476-47FC-970E-F00D99CDBAB3",
      "token" : "0x00000",
      "native_offset" : "0x0",
      "filename" : "MonoDevelop.MSBuildBuilder.exe",
      "sizeofimage" : "0x18000",
      "timestamp" : "0xc077b0d4",
      "il_offset" : "0x0002a"
   }
,
  {
      "is_managed" : "false",
      "native_address" : "unregistered"
   }
,
  {
      "is_managed" : "true",
      "guid" : "55ADAE45-46CD-485B-A70E-2948332EBE8C",
      "token" : "0x00000",
      "native_offset" : "0x0",
      "filename" : "mscorlib.dll",
      "sizeofimage" : "0x474000",
      "timestamp" : "0xcdf122ed",
      "il_offset" : "0x0000c"
   }
,
  {
      "is_managed" : "true",
      "guid" : "55ADAE45-46CD-485B-A70E-2948332EBE8C",
      "token" : "0x6004ced",
      "native_offset" : "0x0",
      "filename" : "mscorlib.dll",
      "sizeofimage" : "0x474000",
      "timestamp" : "0xcdf122ed",
      "il_offset" : "0x0006a"
   }
,
  {
      "is_managed" : "true",
      "guid" : "55ADAE45-46CD-485B-A70E-2948332EBE8C",
      "token" : "0x60048d1",
      "native_offset" : "0x0",
      "filename" : "mscorlib.dll",
      "sizeofimage" : "0x474000",
      "timestamp" : "0xcdf122ed",
      "il_offset" : "0x00000"
   }
,
  {
      "is_managed" : "true",
      "guid" : "E5BBCD86-B476-47FC-970E-F00D99CDBAB3",
      "token" : "0x6000039",
      "native_offset" : "0x0",
      "filename" : "MonoDevelop.MSBuildBuilder.exe",
      "sizeofimage" : "0x18000",
      "timestamp" : "0xc077b0d4",
      "il_offset" : "0x00019"
   }
,
  {
      "is_managed" : "true",
      "guid" : "E5BBCD86-B476-47FC-970E-F00D99CDBAB3",
      "token" : "0x6000169",
      "native_offset" : "0x0",
      "filename" : "MonoDevelop.MSBuildBuilder.exe",
      "sizeofimage" : "0x18000",
      "timestamp" : "0xc077b0d4",
      "il_offset" : "0x00029"
   }
,
  {
      "is_managed" : "true",
      "guid" : "E5BBCD86-B476-47FC-970E-F00D99CDBAB3",
      "token" : "0x6000184",
      "native_offset" : "0x0",
      "filename" : "MonoDevelop.MSBuildBuilder.exe",
      "sizeofimage" : "0x18000",
      "timestamp" : "0xc077b0d4",
      "il_offset" : "0x00001"
   }
,
  {
      "is_managed" : "true",
      "guid" : "55ADAE45-46CD-485B-A70E-2948332EBE8C",
      "token" : "0x6001ff3",
      "native_offset" : "0x0",
      "filename" : "mscorlib.dll",
      "sizeofimage" : "0x474000",
      "timestamp" : "0xcdf122ed",
      "il_offset" : "0x00007"
   }
,
  {
      "is_managed" : "true",
      "guid" : "55ADAE45-46CD-485B-A70E-2948332EBE8C",
      "token" : "0x6001ece",
      "native_offset" : "0x0",
      "filename" : "mscorlib.dll",
      "sizeofimage" : "0x474000",
      "timestamp" : "0xcdf122ed",
      "il_offset" : "0x00071"
   }
,
  {
      "is_managed" : "true",
      "guid" : "55ADAE45-46CD-485B-A70E-2948332EBE8C",
      "token" : "0x6001ecc",
      "native_offset" : "0x0",
      "filename" : "mscorlib.dll",
      "sizeofimage" : "0x474000",
      "timestamp" : "0xcdf122ed",
      "il_offset" : "0x00000"
   }
,
  {
      "is_managed" : "true",
      "guid" : "55ADAE45-46CD-485B-A70E-2948332EBE8C",
      "token" : "0x6001ff1",
      "native_offset" : "0x0",
      "filename" : "mscorlib.dll",
      "sizeofimage" : "0x474000",
      "timestamp" : "0xcdf122ed",
      "il_offset" : "0x00021"
   }
,
  {
      "is_managed" : "true",
      "guid" : "55ADAE45-46CD-485B-A70E-2948332EBE8C",
      "token" : "0x6001fd9",
      "native_offset" : "0x0",
      "filename" : "mscorlib.dll",
      "sizeofimage" : "0x474000",
      "timestamp" : "0xcdf122ed",
      "il_offset" : "0x00074"
   }
,
  {
      "is_managed" : "true",
      "guid" : "55ADAE45-46CD-485B-A70E-2948332EBE8C",
      "token" : "0x6001fee",
      "native_offset" : "0x0",
      "filename" : "mscorlib.dll",
      "sizeofimage" : "0x474000",
      "timestamp" : "0xcdf122ed",
      "il_offset" : "0x00000"
   }
,
  {
      "is_managed" : "true",
      "guid" : "55ADAE45-46CD-485B-A70E-2948332EBE8C",
      "token" : "0x00000",
      "native_offset" : "0x0",
      "filename" : "mscorlib.dll",
      "sizeofimage" : "0x474000",
      "timestamp" : "0xcdf122ed",
      "il_offset" : "0x0002a"
   }

  ],
  "unmanaged_frames" : [
 {
    "is_managed" : "false",
    "native_address" : "0x108fa7346",
    "native_offset" : "0x00000"
  }
,
 {
    "is_managed" : "false",
    "native_address" : "0x109141aa5",
    "native_offset" : "0x00000"
  }
,
 {
    "is_managed" : "false",
    "native_address" : "0x10914211a",
    "native_offset" : "0x00000"
  }
,
 {
    "is_managed" : "false",
    "native_address" : "0x109013da7",
    "native_offset" : "0x00000"
  }
,
 {
    "is_managed" : "false",
    "native_address" : "0x108fabfb5",
    "native_offset" : "0x00000"
  }
,
 {
    "is_managed" : "false",
    "native_address" : "0x10901309f",
    "native_offset" : "0x00000"
  }
,
 {
    "is_managed" : "false",
    "native_address" : "0x7fff79497b3d",
    "native_offset" : "0x00000"
  }
,
 {
    "is_managed" : "false",
    "native_address" : "0x10926ccbc",
    "native_offset" : "0x00000"
  }
,
 {
    "is_managed" : "false",
    "native_address" : "0x7fff793561c9",
    "native_offset" : "0x00000"
  }
,
 {
    "is_managed" : "false",
    "native_address" : "0x109211397",
    "native_offset" : "0x00000"
  }
,
 {
    "is_managed" : "false",
    "native_address" : "0x1091f227f",
    "native_offset" : "0x00000"
  }
,
 {
    "is_managed" : "false",
    "native_address" : "0x10921171e",
    "native_offset" : "0x00000"
  }
,
 {
    "is_managed" : "false",
    "native_address" : "0x10921189f",
    "native_offset" : "0x00000"
  }
,
 {
    "is_managed" : "false",
    "native_address" : "0x1090ae059",
    "native_offset" : "0x00000"
  }
,
 {
    "is_managed" : "false",
    "native_address" : "0x1090ae5f2",
    "native_offset" : "0x00000"
  }
,
 {
    "is_managed" : "false",
    "native_address" : "0x1091ff6d1",
    "native_offset" : "0x00000"
  }
,
 {
    "is_managed" : "false",
    "native_address" : "0x1091ffa70",
    "native_offset" : "0x00000"
  }
,
 {
    "is_managed" : "false",
    "native_address" : "0x1090b0706",
    "native_offset" : "0x00000"
  }
,
 {
    "is_managed" : "false",
    "native_address" : "0x1090d4ab4",
    "native_offset" : "0x00000"
  }
,
 {
    "is_managed" : "true",
    "guid" : "55ADAE45-46CD-485B-A70E-2948332EBE8C",
    "token" : "0x00000",
    "native_offset" : "0x0",
    "filename" : "mscorlib.dll",
    "sizeofimage" : "0x474000",
    "timestamp" : "0xcdf122ed",
    "il_offset" : "0x00000"
  }
,
 {
    "is_managed" : "true",
    "guid" : "55ADAE45-46CD-485B-A70E-2948332EBE8C",
    "token" : "0x6001f8c",
    "native_offset" : "0x0",
    "filename" : "mscorlib.dll",
    "sizeofimage" : "0x474000",
    "timestamp" : "0xcdf122ed",
    "il_offset" : "0x00000"
  }
,
 {
    "is_managed" : "true",
    "guid" : "E5BBCD86-B476-47FC-970E-F00D99CDBAB3",
    "token" : "0x6000083",
    "native_offset" : "0x0",
    "filename" : "MonoDevelop.MSBuildBuilder.exe",
    "sizeofimage" : "0x18000",
    "timestamp" : "0xc077b0d4",
    "il_offset" : "0x00000"
  }
,
 {
    "is_managed" : "true",
    "guid" : "E5BBCD86-B476-47FC-970E-F00D99CDBAB3",
    "token" : "0x600006a",
    "native_offset" : "0x0",
    "filename" : "MonoDevelop.MSBuildBuilder.exe",
    "sizeofimage" : "0x18000",
    "timestamp" : "0xc077b0d4",
    "il_offset" : "0x00000"
  }
,
 {
    "is_managed" : "true",
    "guid" : "E5BBCD86-B476-47FC-970E-F00D99CDBAB3",
    "token" : "0x60000a1",
    "native_offset" : "0x0",
    "filename" : "MonoDevelop.MSBuildBuilder.exe",
    "sizeofimage" : "0x18000",
    "timestamp" : "0xc077b0d4",
    "il_offset" : "0x00000"
  }
,
 {
    "is_managed" : "true",
    "guid" : "E5BBCD86-B476-47FC-970E-F00D99CDBAB3",
    "token" : "0x6000067",
    "native_offset" : "0x0",
    "filename" : "MonoDevelop.MSBuildBuilder.exe",
    "sizeofimage" : "0x18000",
    "timestamp" : "0xc077b0d4",
    "il_offset" : "0x00000"
  }
,
 {
    "is_managed" : "true",
    "guid" : "E5BBCD86-B476-47FC-970E-F00D99CDBAB3",
    "token" : "0x6000075",
    "native_offset" : "0x0",
    "filename" : "MonoDevelop.MSBuildBuilder.exe",
    "sizeofimage" : "0x18000",
    "timestamp" : "0xc077b0d4",
    "il_offset" : "0x00000"
  }
,
 {
    "is_managed" : "true",
    "guid" : "E5BBCD86-B476-47FC-970E-F00D99CDBAB3",
    "token" : "0x00000",
    "native_offset" : "0x0",
    "filename" : "MonoDevelop.MSBuildBuilder.exe",
    "sizeofimage" : "0x18000",
    "timestamp" : "0xc077b0d4",
    "il_offset" : "0x00000"
  }
,
 {
    "is_managed" : "false",
    "native_address" : "0x108f09ae2",
    "native_offset" : "0x00000"
  }
,
 {
    "is_managed" : "false",
    "native_address" : "0x109117967",
    "native_offset" : "0x00000"
  }
,
 {
    "is_managed" : "false",
    "native_address" : "0x109120409",
    "native_offset" : "0x00000"
  }
,
 {
    "is_managed" : "false",
    "native_address" : "0x1090b838d",
    "native_offset" : "0x00000"
  }
,
 {
    "is_managed" : "false",
    "native_address" : "0x1090cc027",
    "native_offset" : "0x00000"
  }
,
 {
    "is_managed" : "true",
    "guid" : "55ADAE45-46CD-485B-A70E-2948332EBE8C",
    "token" : "0x00000",
    "native_offset" : "0x0",
    "filename" : "mscorlib.dll",
    "sizeofimage" : "0x474000",
    "timestamp" : "0xcdf122ed",
    "il_offset" : "0x00000"
  }
,
 {
    "is_managed" : "true",
    "guid" : "55ADAE45-46CD-485B-A70E-2948332EBE8C",
    "token" : "0x6004ced",
    "native_offset" : "0x0",
    "filename" : "mscorlib.dll",
    "sizeofimage" : "0x474000",
    "timestamp" : "0xcdf122ed",
    "il_offset" : "0x00000"
  }
,
 {
    "is_managed" : "true",
    "guid" : "55ADAE45-46CD-485B-A70E-2948332EBE8C",
    "token" : "0x60048d1",
    "native_offset" : "0x0",
    "filename" : "mscorlib.dll",
    "sizeofimage" : "0x474000",
    "timestamp" : "0xcdf122ed",
    "il_offset" : "0x00000"
  }
,
 {
    "is_managed" : "true",
    "guid" : "E5BBCD86-B476-47FC-970E-F00D99CDBAB3",
    "token" : "0x6000169",
    "native_offset" : "0x0",
    "filename" : "MonoDevelop.MSBuildBuilder.exe",
    "sizeofimage" : "0x18000",
    "timestamp" : "0xc077b0d4",
    "il_offset" : "0x00000"
  }
,
 {
    "is_managed" : "true",
    "guid" : "E5BBCD86-B476-47FC-970E-F00D99CDBAB3",
    "token" : "0x6000184",
    "native_offset" : "0x0",
    "filename" : "MonoDevelop.MSBuildBuilder.exe",
    "sizeofimage" : "0x18000",
    "timestamp" : "0xc077b0d4",
    "il_offset" : "0x00000"
  }
,
 {
    "is_managed" : "true",
    "guid" : "55ADAE45-46CD-485B-A70E-2948332EBE8C",
    "token" : "0x6001ff3",
    "native_offset" : "0x0",
    "filename" : "mscorlib.dll",
    "sizeofimage" : "0x474000",
    "timestamp" : "0xcdf122ed",
    "il_offset" : "0x00000"
  }
,
 {
    "is_managed" : "true",
    "guid" : "55ADAE45-46CD-485B-A70E-2948332EBE8C",
    "token" : "0x6001ecc",
    "native_offset" : "0x0",
    "filename" : "mscorlib.dll",
    "sizeofimage" : "0x474000",
    "timestamp" : "0xcdf122ed",
    "il_offset" : "0x00000"
  }
,
 {
    "is_managed" : "true",
    "guid" : "55ADAE45-46CD-485B-A70E-2948332EBE8C",
    "token" : "0x6001fee",
    "native_offset" : "0x0",
    "filename" : "mscorlib.dll",
    "sizeofimage" : "0x474000",
    "timestamp" : "0xcdf122ed",
    "il_offset" : "0x00000"
  }
,
 {
    "is_managed" : "false",
    "native_address" : "0x108f09ae2",
    "native_offset" : "0x00000"
  }
,
 {
    "is_managed" : "false",
    "native_address" : "0x109119342",
    "native_offset" : "0x00000"
  }
,
 {
    "is_managed" : "false",
    "native_address" : "0x1091451c7",
    "native_offset" : "0x00000"
  }
,
 {
    "is_managed" : "false",
    "native_address" : "0x109078f88",
    "native_offset" : "0x00000"
  }
,
 {
    "is_managed" : "false",
    "native_address" : "0x1091426ed",
    "native_offset" : "0x00000"
  }
,
 {
    "is_managed" : "false",
    "native_address" : "0x7fff794a0339",
    "native_offset" : "0x00000"
  }
,
 {
    "is_managed" : "false",
    "native_address" : "0x7fff794a32a7",
    "native_offset" : "0x00000"
  }
,
 {
    "is_managed" : "false",
    "native_address" : "0x7fff7949f445",
    "native_offset" : "0x00000"
  }

 ]
},
{
  "is_managed" : false,
  "offset_free_hash" : "0xb38e38cc",
  "offset_rich_hash" : "0xb38e38cc",
  "crashed" : false,
  "native_thread_id" : "0x70000d909000",
  "thread_info_addr" : "0x7ffb32000000",
  "thread_name" : "Finalizer",
  "ctx" : {
    "IP" : "0x7fff793e6c66",
    "SP" : "0x70000d908e18",
    "BP" : "0x70000d908e60"
 },
  "unmanaged_frames" : [
 {
    "is_managed" : "false",
    "native_address" : "0x108fa7346",
    "native_offset" : "0x00000"
  }
,
 {
    "is_managed" : "false",
    "native_address" : "0x109141aa5",
    "native_offset" : "0x00000"
  }
,
 {
    "is_managed" : "false",
    "native_address" : "0x1091417d7",
    "native_offset" : "0x00000"
  }
,
 {
    "is_managed" : "false",
    "native_address" : "0x109012ce0",
    "native_offset" : "0x00000"
  }
,
 {
    "is_managed" : "false",
    "native_address" : "0x7fff79497b3d",
    "native_offset" : "0x00000"
  }
,
 {
    "is_managed" : "true",
    "guid" : "55ADAE45-46CD-485B-A70E-2948332EBE8C",
    "token" : "0x6001467",
    "native_offset" : "0x0",
    "filename" : "mscorlib.dll",
    "sizeofimage" : "0x474000",
    "timestamp" : "0xcdf122ed",
    "il_offset" : "0x00000"
  }
,
 {
    "is_managed" : "false",
    "native_address" : "0x1091426ed",
    "native_offset" : "0x00000"
  }
,
 {
    "is_managed" : "false",
    "native_address" : "0x7fff794a0339",
    "native_offset" : "0x00000"
  }
,
 {
    "is_managed" : "false",
    "native_address" : "0x7fff794a32a7",
    "native_offset" : "0x00000"
  }
,
 {
    "is_managed" : "false",
    "native_address" : "0x7fff7949f445",
    "native_offset" : "0x00000"
  }

 ]
}
]
}